{
  "node": {
    "7f348d1be20556fc87706dd5eaabcc8b8ed257c311": {
      "workers": {
        "app/(auth)/sign-in/[[...sign-in]]/page": {
          "moduleId": "(action-browser)/./node_modules/next/dist/build/webpack/loaders/next-flight-action-entry-loader.js?actions=%5B%5B%22%2Fhome%2Fkundan%2FDeveloper%2Fhrms-v-001%2Fclient%2Fnode_modules%2F%40clerk%2Fnextjs%2Fdist%2Fesm%2Fapp-router%2Fkeyless-actions.js%22%2C%5B%5B%227f348d1be20556fc87706dd5eaabcc8b8ed257c311%22%2C%22createOrReadKeylessAction%22%5D%2C%5B%227f62fc685b6cdcfaa9917d3a8f1e6ba84f1af33af6%22%2C%22syncKeylessConfigAction%22%5D%5D%5D%2C%5B%22%2Fhome%2Fkundan%2FDeveloper%2Fhrms-v-001%2Fclient%2Fnode_modules%2F%40clerk%2Fnextjs%2Fdist%2Fesm%2Fapp-router%2Fserver-actions.js%22%2C%5B%5B%227f146bf20452dc07388163201ff09e79b53645845a%22%2C%22invalidateCacheAction%22%5D%5D%5D%5D&__client_imported__=true!",
          "async": false
        },
        "app/_not-found/page": {
          "moduleId": "(action-browser)/./node_modules/next/dist/build/webpack/loaders/next-flight-action-entry-loader.js?actions=%5B%5B%22%2Fhome%2Fkundan%2FDeveloper%2Fhrms-v-001%2Fclient%2Fnode_modules%2F%40clerk%2Fnextjs%2Fdist%2Fesm%2Fapp-router%2Fkeyless-actions.js%22%2C%5B%5B%227f348d1be20556fc87706dd5eaabcc8b8ed257c311%22%2C%22createOrReadKeylessAction%22%5D%2C%5B%227f62fc685b6cdcfaa9917d3a8f1e6ba84f1af33af6%22%2C%22syncKeylessConfigAction%22%5D%5D%5D%2C%5B%22%2Fhome%2Fkundan%2FDeveloper%2Fhrms-v-001%2Fclient%2Fnode_modules%2F%40clerk%2Fnextjs%2Fdist%2Fesm%2Fapp-router%2Fserver-actions.js%22%2C%5B%5B%227f146bf20452dc07388163201ff09e79b53645845a%22%2C%22invalidateCacheAction%22%5D%5D%5D%5D&__client_imported__=true!",
          "async": false
        }
      },
      "layer": {
        "app/(auth)/sign-in/[[...sign-in]]/page": "action-browser",
        "app/_not-found/page": "action-browser"
      }
    },
    "7f62fc685b6cdcfaa9917d3a8f1e6ba84f1af33af6": {
      "workers": {
        "app/(auth)/sign-in/[[...sign-in]]/page": {
          "moduleId": "(action-browser)/./node_modules/next/dist/build/webpack/loaders/next-flight-action-entry-loader.js?actions=%5B%5B%22%2Fhome%2Fkundan%2FDeveloper%2Fhrms-v-001%2Fclient%2Fnode_modules%2F%40clerk%2Fnextjs%2Fdist%2Fesm%2Fapp-router%2Fkeyless-actions.js%22%2C%5B%5B%227f348d1be20556fc87706dd5eaabcc8b8ed257c311%22%2C%22createOrReadKeylessAction%22%5D%2C%5B%227f62fc685b6cdcfaa9917d3a8f1e6ba84f1af33af6%22%2C%22syncKeylessConfigAction%22%5D%5D%5D%2C%5B%22%2Fhome%2Fkundan%2FDeveloper%2Fhrms-v-001%2Fclient%2Fnode_modules%2F%40clerk%2Fnextjs%2Fdist%2Fesm%2Fapp-router%2Fserver-actions.js%22%2C%5B%5B%227f146bf20452dc07388163201ff09e79b53645845a%22%2C%22invalidateCacheAction%22%5D%5D%5D%5D&__client_imported__=true!",
          "async": false
        },
        "app/_not-found/page": {
          "moduleId": "(action-browser)/./node_modules/next/dist/build/webpack/loaders/next-flight-action-entry-loader.js?actions=%5B%5B%22%2Fhome%2Fkundan%2FDeveloper%2Fhrms-v-001%2Fclient%2Fnode_modules%2F%40clerk%2Fnextjs%2Fdist%2Fesm%2Fapp-router%2Fkeyless-actions.js%22%2C%5B%5B%227f348d1be20556fc87706dd5eaabcc8b8ed257c311%22%2C%22createOrReadKeylessAction%22%5D%2C%5B%227f62fc685b6cdcfaa9917d3a8f1e6ba84f1af33af6%22%2C%22syncKeylessConfigAction%22%5D%5D%5D%2C%5B%22%2Fhome%2Fkundan%2FDeveloper%2Fhrms-v-001%2Fclient%2Fnode_modules%2F%40clerk%2Fnextjs%2Fdist%2Fesm%2Fapp-router%2Fserver-actions.js%22%2C%5B%5B%227f146bf20452dc07388163201ff09e79b53645845a%22%2C%22invalidateCacheAction%22%5D%5D%5D%5D&__client_imported__=true!",
          "async": false
        }
      },
      "layer": {
        "app/(auth)/sign-in/[[...sign-in]]/page": "action-browser",
        "app/_not-found/page": "action-browser"
      }
    },
    "7f146bf20452dc07388163201ff09e79b53645845a": {
      "workers": {
        "app/(auth)/sign-in/[[...sign-in]]/page": {
          "moduleId": "(action-browser)/./node_modules/next/dist/build/webpack/loaders/next-flight-action-entry-loader.js?actions=%5B%5B%22%2Fhome%2Fkundan%2FDeveloper%2Fhrms-v-001%2Fclient%2Fnode_modules%2F%40clerk%2Fnextjs%2Fdist%2Fesm%2Fapp-router%2Fkeyless-actions.js%22%2C%5B%5B%227f348d1be20556fc87706dd5eaabcc8b8ed257c311%22%2C%22createOrReadKeylessAction%22%5D%2C%5B%227f62fc685b6cdcfaa9917d3a8f1e6ba84f1af33af6%22%2C%22syncKeylessConfigAction%22%5D%5D%5D%2C%5B%22%2Fhome%2Fkundan%2FDeveloper%2Fhrms-v-001%2Fclient%2Fnode_modules%2F%40clerk%2Fnextjs%2Fdist%2Fesm%2Fapp-router%2Fserver-actions.js%22%2C%5B%5B%227f146bf20452dc07388163201ff09e79b53645845a%22%2C%22invalidateCacheAction%22%5D%5D%5D%5D&__client_imported__=true!",
          "async": false
        },
        "app/_not-found/page": {
          "moduleId": "(action-browser)/./node_modules/next/dist/build/webpack/loaders/next-flight-action-entry-loader.js?actions=%5B%5B%22%2Fhome%2Fkundan%2FDeveloper%2Fhrms-v-001%2Fclient%2Fnode_modules%2F%40clerk%2Fnextjs%2Fdist%2Fesm%2Fapp-router%2Fkeyless-actions.js%22%2C%5B%5B%227f348d1be20556fc87706dd5eaabcc8b8ed257c311%22%2C%22createOrReadKeylessAction%22%5D%2C%5B%227f62fc685b6cdcfaa9917d3a8f1e6ba84f1af33af6%22%2C%22syncKeylessConfigAction%22%5D%5D%5D%2C%5B%22%2Fhome%2Fkundan%2FDeveloper%2Fhrms-v-001%2Fclient%2Fnode_modules%2F%40clerk%2Fnextjs%2Fdist%2Fesm%2Fapp-router%2Fserver-actions.js%22%2C%5B%5B%227f146bf20452dc07388163201ff09e79b53645845a%22%2C%22invalidateCacheAction%22%5D%5D%5D%5D&__client_imported__=true!",
          "async": false
        }
      },
      "layer": {
        "app/(auth)/sign-in/[[...sign-in]]/page": "action-browser",
        "app/_not-found/page": "action-browser"
      }
    }
  },
  "edge": {},
  "encryptionKey": "eSdExfyfHjVaWeP+pTu6YeKOeP1V/ggKWeqxCPrqdt4="
}